cima/goes/images/__init__.py
cima/goes/images/clipping.py
cima/goes/images/data_types.py
cima/goes/images/dataset.py
cima/goes/images/figure_sizing.py
cima/goes/images/images.py
cima/goes/images/load_cpt.py
cima/goes/images/palettes.py
cima/goes/images/smn_topes.cpt
cima_goes_images-0.1b5.data/data/LICENSE
cima_goes_images-0.1b5.dist-info/LICENSE
cima_goes_images-0.1b5.dist-info/METADATA
cima_goes_images-0.1b5.dist-info/WHEEL
cima_goes_images-0.1b5.dist-info/top_level.txt
cima_goes_images-0.1b5.dist-info/RECORD
