Metadata-Version: 2.1
Name: cima-goes-images
Version: 0.1b5
Summary: Generate Images from GOES-16 Files
Home-page: https://github.com/garciafido/cima-goes-images
Author: Fido Garcia
Author-email: garciafido@gmail.com
License: MIT
Platform: UNKNOWN
Classifier: Programming Language :: Python :: 3
Classifier: License :: OSI Approved :: MIT License
Classifier: Operating System :: OS Independent
Requires-Python: >=3.8
